mqt/yaqs/__init__.py
mqt/yaqs/_version.py
mqt/yaqs/_version.pyi
mqt/yaqs/simulator.py
mqt/yaqs/analog/__init__.py
mqt/yaqs/analog/analog_tjm.py
mqt/yaqs/core/__init__.py
mqt/yaqs/core/data_structures/__init__.py
mqt/yaqs/core/data_structures/networks.py
mqt/yaqs/core/data_structures/noise_model.py
mqt/yaqs/core/data_structures/simulation_parameters.py
mqt/yaqs/core/libraries/__init__.py
mqt/yaqs/core/libraries/circuit_library.py
mqt/yaqs/core/libraries/circuit_library_utils.py
mqt/yaqs/core/libraries/gate_library.py
mqt/yaqs/core/libraries/noise_library.py
mqt/yaqs/core/methods/__init__.py
mqt/yaqs/core/methods/bug.py
mqt/yaqs/core/methods/decompositions.py
mqt/yaqs/core/methods/dissipation.py
mqt/yaqs/core/methods/matrix_exponential.py
mqt/yaqs/core/methods/stochastic_process.py
mqt/yaqs/core/methods/tdvp.py
mqt/yaqs/digital/__init__.py
mqt/yaqs/digital/digital_tjm.py
mqt/yaqs/digital/equivalence_checker.py
mqt/yaqs/digital/utils/__init__.py
mqt/yaqs/digital/utils/dag_utils.py
mqt/yaqs/digital/utils/mpo_utils.py
mqt_yaqs-0.3.2.dist-info/METADATA
mqt_yaqs-0.3.2.dist-info/WHEEL
mqt_yaqs-0.3.2.dist-info/licenses/LICENSE.md
mqt_yaqs-0.3.2.dist-info/RECORD
