Metadata-Version: 2.4
Name: mqt-yaqs
Version: 0.3.2
Summary: A Tool for Simulating Open Quantum Systems, Noisy Quantum Circuits, and Realistic Quantum Hardware
Project-URL: Homepage, https://github.com/munich-quantum-toolkit/yaqs
Project-URL: Documentation, https://mqt.readthedocs.io/projects/yaqs
Project-URL: Issues, https://github.com/munich-quantum-toolkit/yaqs/issues
Project-URL: Discussions, https://github.com/munich-quantum-toolkit/yaqs/discussions
Author-email: Aaron Sander <aaron.sander@tum.de>
Maintainer-email: Lukas Burgholzer <burgholzer@me.com>
License-Expression: MIT
License-File: LICENSE.md
Keywords: MQT,quantum-computing,quantum-simulation,tensor-networks
Classifier: Development Status :: 4 - Beta
Classifier: Intended Audience :: Science/Research
Classifier: Natural Language :: English
Classifier: Operating System :: MacOS
Classifier: Operating System :: Microsoft :: Windows
Classifier: Operating System :: POSIX :: Linux
Classifier: Programming Language :: Python
Classifier: Programming Language :: Python :: 3 :: Only
Classifier: Programming Language :: Python :: 3.10
Classifier: Programming Language :: Python :: 3.11
Classifier: Programming Language :: Python :: 3.12
Classifier: Programming Language :: Python :: 3.13
Classifier: Programming Language :: Python :: 3.14
Classifier: Topic :: Scientific/Engineering :: Electronic Design Automation (EDA)
Classifier: Typing :: Typed
Requires-Python: >=3.10
Requires-Dist: numpy>=1.23.0
Requires-Dist: numpy>=1.24; python_version >= '3.11'
Requires-Dist: numpy>=1.26; python_version >= '3.12'
Requires-Dist: numpy>=2.1; python_version >= '3.13'
Requires-Dist: numpy>=2.3.2; python_version >= '3.14'
Requires-Dist: opt-einsum>=3.4.0
Requires-Dist: qiskit>=1.1.0
Requires-Dist: qiskit>=1.3.0; python_version >= '3.13'
Requires-Dist: scipy>=1.13.1
Requires-Dist: scipy>=1.14.1; python_version >= '3.13'
Requires-Dist: scipy>=1.16.1; python_version >= '3.14'
Requires-Dist: tqdm>=4.67.1
